xsxx/__init__.py
xsxx/base_channel.py
xsxx/util.py
xsxx/xsxx_channel.py
SmsHttpChannel-0.0.2.dist-info/LICENSE
SmsHttpChannel-0.0.2.dist-info/METADATA
SmsHttpChannel-0.0.2.dist-info/WHEEL
SmsHttpChannel-0.0.2.dist-info/top_level.txt
SmsHttpChannel-0.0.2.dist-info/RECORD
