Metadata-Version: 2.1
Name: SmsHttpChannel
Version: 0.0.2
Summary: Python异步提交短信的模块
Home-page: https://gitee.com/pysuk/SmsHttpChannel.git
Author: suk
Author-email: 277667028@qq.com
License: UNKNOWN
Platform: UNKNOWN
Classifier: Programming Language :: Python :: 3
Classifier: License :: OSI Approved :: MIT License
Classifier: Operating System :: OS Independent
Requires-Python: >=3
Requires-Dist: tornado (==6.1)
